pyelink_connector/__init__.py
pyelink_connector/utils.py
pyelink_connector/psychopy/__init__.py
pyelink_connector/psychopy/connector.py
pyelink_connector/psychopy/utils.py
pyelink_connector/pygame/__init__.py
pyelink_connector/pygame/connector.py
pyelink_connector/pygame/utils.py
pyelink_connector/pyglet/__init__.py
pyelink_connector/pyglet/connector.py
pyelink_connector/pyglet/utils.py
pyelink_connector-0.2.0.dist-info/METADATA
pyelink_connector-0.2.0.dist-info/WHEEL
pyelink_connector-0.2.0.dist-info/licenses/LICENSE
pyelink_connector-0.2.0.dist-info/RECORD
