Metadata-Version: 2.4
Name: pyelink_connector
Version: 0.2.0
Summary: A small EyeLink 1000+ connector class using pylink and supporting pygame and pyglet applications.
Project-URL: Homepage, https://github.com/uvest/pyelink_connector
Project-URL: Issues, https://github.com/uvest/pyelink_connector/issues
Author-email: Kai Streiling <kai.streiling@gmail.com>
License-Expression: MIT
License-File: LICENSE
Classifier: Operating System :: OS Independent
Classifier: Programming Language :: Python :: 3
Requires-Python: >=3.10
Provides-Extra: psychopy
Requires-Dist: psychopy>=2024.2.0; extra == 'psychopy'
Provides-Extra: pygame
Requires-Dist: pygame-ce>=2.5.0; extra == 'pygame'
Provides-Extra: pyglet
Requires-Dist: pyglet>=2.0.0; extra == 'pyglet'
Requires-Dist: screeninfo>=0.8.1; extra == 'pyglet'
